{
  "main": {
    "id": "c4f7fdb608baf8e1",
    "type": "split",
    "children": [
      {
        "id": "097d9d2b93c9689b",
        "type": "tabs",
        "children": [
          {
            "id": "d236a053c6f1f5a2",
            "type": "leaf",
            "pane-relief:history-v1": {
              "pos": 0,
              "stack": [
                {
                  "state": "{}",
                  "eState": "{}"
                },
                {
                  "title": "202507302207 RAC - contents",
                  "icon": "lucide-file",
                  "state": "{\"type\":\"markdown\",\"state\":{\"file\":\"Atlas/Projects/Zoimmeisdess/produits/RAC - Revenir en accord avec son corps/202507302207 RAC - contents.md\",\"mode\":\"source\",\"source\":false,\"backlinks\":true,\"backlinkOpts\":{\"collapseAll\":false,\"extraContext\":false,\"sortOrder\":\"alphabetical\",\"showSearch\":false,\"searchQuery\":\"\",\"backlinkCollapsed\":false,\"unlinkedCollapsed\":true}},\"icon\":\"lucide-file\",\"title\":\"202507302207 RAC - contents\"}",
                  "eState": "{\"cursor\":{\"from\":{\"line\":26,\"ch\":23},\"to\":{\"line\":26,\"ch\":23}},\"scroll\":24.847748815165875}"
                },
                {
                  "title": "202507112258 NL 24",
                  "icon": "lucide-file",
                  "state": "{\"type\":\"markdown\",\"state\":{\"file\":\"Atlas/Notes/BooksNotes/202507112258 NL 24.md\",\"mode\":\"source\",\"source\":false,\"backlinks\":true,\"backlinkOpts\":{\"collapseAll\":false,\"extraContext\":false,\"sortOrder\":\"alphabetical\",\"showSearch\":false,\"searchQuery\":\"\",\"backlinkCollapsed\":false,\"unlinkedCollapsed\":true}},\"icon\":\"lucide-file\",\"title\":\"202507112258 NL 24\"}",
                  "eState": "{\"cursor\":{\"from\":{\"line\":0,\"ch\":0},\"to\":{\"line\":0,\"ch\":0}}}"
                },
                {
                  "title": "202507112258 NL 23",
                  "icon": "lucide-file",
                  "state": "{\"type\":\"markdown\",\"state\":{\"file\":\"Atlas/Notes/BooksNotes/202507112258 NL 23.md\",\"mode\":\"source\",\"source\":false,\"backlinks\":true,\"backlinkOpts\":{\"collapseAll\":false,\"extraContext\":false,\"sortOrder\":\"alphabetical\",\"showSearch\":false,\"searchQuery\":\"\",\"backlinkCollapsed\":false,\"unlinkedCollapsed\":true}},\"icon\":\"lucide-file\",\"title\":\"202507112258 NL 23\"}",
                  "eState": "{\"cursor\":{\"from\":{\"line\":0,\"ch\":0},\"to\":{\"line\":0,\"ch\":0}}}"
                },
                {
                  "title": "202507112258 NL 8",
                  "icon": "lucide-file",
                  "state": "{\"type\":\"markdown\",\"state\":{\"file\":\"Atlas/Notes/BooksNotes/202507112258 NL 8.md\",\"mode\":\"source\",\"source\":false,\"backlinks\":true,\"backlinkOpts\":{\"collapseAll\":false,\"extraContext\":false,\"sortOrder\":\"alphabetical\",\"showSearch\":false,\"searchQuery\":\"\",\"backlinkCollapsed\":false,\"unlinkedCollapsed\":true}},\"icon\":\"lucide-file\",\"title\":\"202507112258 NL 8\"}",
                  "eState": "{\"cursor\":{\"from\":{\"line\":0,\"ch\":0},\"to\":{\"line\":0,\"ch\":0}}}"
                },
                {
                  "title": "Integral",
                  "icon": "lucide-file",
                  "state": "{\"type\":\"markdown\",\"state\":{\"file\":\"Atlas/Maps/Integral.md\",\"mode\":\"source\",\"source\":false,\"backlinks\":true,\"backlinkOpts\":{\"collapseAll\":false,\"extraContext\":false,\"sortOrder\":\"alphabetical\",\"showSearch\":false,\"searchQuery\":\"\",\"backlinkCollapsed\":false,\"unlinkedCollapsed\":true}},\"icon\":\"lucide-file\",\"title\":\"Integral\"}",
                  "eState": "{\"cursor\":{\"from\":{\"line\":10,\"ch\":16},\"to\":{\"line\":10,\"ch\":16}},\"scroll\":0}"
                },
                {
                  "title": "202507112258 NL 24",
                  "icon": "lucide-file",
                  "state": "{\"type\":\"markdown\",\"state\":{\"file\":\"Atlas/Notes/BooksNotes/202507112258 NL 24.md\",\"mode\":\"source\",\"source\":false,\"backlinks\":true,\"backlinkOpts\":{\"collapseAll\":false,\"extraContext\":false,\"sortOrder\":\"alphabetical\",\"showSearch\":false,\"searchQuery\":\"\",\"backlinkCollapsed\":false,\"unlinkedCollapsed\":true}},\"icon\":\"lucide-file\",\"title\":\"202507112258 NL 24\"}",
                  "eState": "{\"cursor\":{\"from\":{\"line\":34,\"ch\":4},\"to\":{\"line\":34,\"ch\":4}},\"scroll\":22.715625445048016}"
                },
                {
                  "title": "Integral",
                  "icon": "lucide-file",
                  "state": "{\"type\":\"markdown\",\"state\":{\"file\":\"Atlas/Maps/Integral.md\",\"mode\":\"source\",\"source\":false,\"backlinks\":true,\"backlinkOpts\":{\"collapseAll\":false,\"extraContext\":false,\"sortOrder\":\"alphabetical\",\"showSearch\":false,\"searchQuery\":\"\",\"backlinkCollapsed\":false,\"unlinkedCollapsed\":true}},\"icon\":\"lucide-file\",\"title\":\"Integral\"}",
                  "eState": "{\"cursor\":{\"from\":{\"line\":26,\"ch\":16},\"to\":{\"line\":26,\"ch\":16}},\"scroll\":16.198437531789143}"
                },
                {
                  "title": "202507112258 NL 23",
                  "icon": "lucide-file",
                  "state": "{\"type\":\"markdown\",\"state\":{\"file\":\"Atlas/Notes/BooksNotes/202507112258 NL 23.md\",\"mode\":\"source\",\"source\":false,\"backlinks\":true,\"backlinkOpts\":{\"collapseAll\":false,\"extraContext\":false,\"sortOrder\":\"alphabetical\",\"showSearch\":false,\"searchQuery\":\"\",\"backlinkCollapsed\":false,\"unlinkedCollapsed\":true}},\"icon\":\"lucide-file\",\"title\":\"202507112258 NL 23\"}",
                  "eState": "{\"cursor\":{\"from\":{\"line\":0,\"ch\":0},\"to\":{\"line\":0,\"ch\":0}},\"scroll\":25.343055301242405}"
                },
                {
                  "title": "202507302245 RAC - V2",
                  "icon": "lucide-file",
                  "state": "{\"type\":\"markdown\",\"state\":{\"file\":\"Atlas/Projects/Zoimmeisdess/produits/RAC - Revenir en accord avec son corps/202507302245 RAC - V2.md\",\"mode\":\"source\",\"source\":false,\"backlinks\":true,\"backlinkOpts\":{\"collapseAll\":false,\"extraContext\":false,\"sortOrder\":\"alphabetical\",\"showSearch\":false,\"searchQuery\":\"\",\"backlinkCollapsed\":false,\"unlinkedCollapsed\":true}},\"icon\":\"lucide-file\",\"title\":\"202507302245 RAC - V2\"}",
                  "eState": "{\"cursor\":{\"from\":{\"line\":112,\"ch\":111},\"to\":{\"line\":112,\"ch\":111}},\"scroll\":102.52678159602388}"
                },
                {
                  "title": "MOA RAC - Revenir en accord avec son corps",
                  "icon": "lucide-file",
                  "state": "{\"type\":\"markdown\",\"state\":{\"file\":\"Atlas/Projects/Zoimmeisdess/produits/RAC - Revenir en accord avec son corps/MOA RAC - Revenir en accord avec son corps.md\",\"mode\":\"source\",\"source\":false,\"backlinks\":true,\"backlinkOpts\":{\"collapseAll\":false,\"extraContext\":false,\"sortOrder\":\"alphabetical\",\"showSearch\":false,\"searchQuery\":\"\",\"backlinkCollapsed\":false,\"unlinkedCollapsed\":true}},\"icon\":\"lucide-file\",\"title\":\"MOA RAC - Revenir en accord avec son corps\"}",
                  "eState": "{\"cursor\":{\"from\":{\"line\":11,\"ch\":16},\"to\":{\"line\":11,\"ch\":16}},\"scroll\":0}"
                },
                {
                  "title": "202507302208 RAC - Coach solopreneur",
                  "icon": "lucide-file",
                  "state": "{\"type\":\"markdown\",\"state\":{\"file\":\"Atlas/Projects/Zoimmeisdess/produits/RAC - Revenir en accord avec son corps/202507302208 RAC - Coach solopreneur.md\",\"mode\":\"source\",\"source\":false,\"backlinks\":true,\"backlinkOpts\":{\"collapseAll\":false,\"extraContext\":false,\"sortOrder\":\"alphabetical\",\"showSearch\":false,\"searchQuery\":\"\",\"backlinkCollapsed\":false,\"unlinkedCollapsed\":true}},\"icon\":\"lucide-file\",\"title\":\"202507302208 RAC - Coach solopreneur\"}",
                  "eState": "{\"cursor\":{\"from\":{\"line\":91,\"ch\":37},\"to\":{\"line\":91,\"ch\":37}},\"scroll\":61.444661458333336}"
                },
                {
                  "title": "MOA RAC - Revenir en accord avec son corps",
                  "icon": "lucide-file",
                  "state": "{\"type\":\"markdown\",\"state\":{\"file\":\"Atlas/Projects/Zoimmeisdess/produits/RAC - Revenir en accord avec son corps/MOA RAC - Revenir en accord avec son corps.md\",\"mode\":\"source\",\"source\":false,\"backlinks\":true,\"backlinkOpts\":{\"collapseAll\":false,\"extraContext\":false,\"sortOrder\":\"alphabetical\",\"showSearch\":false,\"searchQuery\":\"\",\"backlinkCollapsed\":false,\"unlinkedCollapsed\":true}},\"icon\":\"lucide-file\",\"title\":\"MOA RAC - Revenir en accord avec son corps\"}",
                  "eState": "{\"cursor\":{\"from\":{\"line\":8,\"ch\":25},\"to\":{\"line\":8,\"ch\":25}},\"scroll\":0}"
                },
                {
                  "title": "202507302207 RAC - contents",
                  "icon": "lucide-file",
                  "state": "{\"type\":\"markdown\",\"state\":{\"file\":\"Atlas/Projects/Zoimmeisdess/produits/RAC - Revenir en accord avec son corps/202507302207 RAC - contents.md\",\"mode\":\"source\",\"source\":false,\"backlinks\":true,\"backlinkOpts\":{\"collapseAll\":false,\"extraContext\":false,\"sortOrder\":\"alphabetical\",\"showSearch\":false,\"searchQuery\":\"\",\"backlinkCollapsed\":false,\"unlinkedCollapsed\":true}},\"icon\":\"lucide-file\",\"title\":\"202507302207 RAC - contents\"}",
                  "eState": "{\"cursor\":{\"from\":{\"line\":11,\"ch\":71},\"to\":{\"line\":11,\"ch\":71}},\"scroll\":21.928317535545023}"
                },
                {
                  "title": "202507302208 RAC - Coach solopreneur",
                  "icon": "lucide-file",
                  "state": "{\"type\":\"markdown\",\"state\":{\"file\":\"Atlas/Projects/Zoimmeisdess/produits/RAC - Revenir en accord avec son corps/202507302208 RAC - Coach solopreneur.md\",\"mode\":\"source\",\"source\":false,\"backlinks\":true,\"backlinkOpts\":{\"collapseAll\":false,\"extraContext\":false,\"sortOrder\":\"alphabetical\",\"showSearch\":false,\"searchQuery\":\"\",\"backlinkCollapsed\":false,\"unlinkedCollapsed\":true}},\"icon\":\"lucide-file\",\"title\":\"202507302208 RAC - Coach solopreneur\"}",
                  "eState": "{\"cursor\":{\"from\":{\"line\":36,\"ch\":0},\"to\":{\"line\":36,\"ch\":0}},\"scroll\":15.461538461538462}"
                },
                {
                  "title": "202507302207 RAC - contents",
                  "icon": "lucide-file",
                  "state": "{\"type\":\"markdown\",\"state\":{\"file\":\"Atlas/Projects/Zoimmeisdess/produits/RAC - Revenir en accord avec son corps/202507302207 RAC - contents.md\",\"mode\":\"source\",\"source\":false,\"backlinks\":true,\"backlinkOpts\":{\"collapseAll\":false,\"extraContext\":false,\"sortOrder\":\"alphabetical\",\"showSearch\":false,\"searchQuery\":\"\",\"backlinkCollapsed\":false,\"unlinkedCollapsed\":true}},\"icon\":\"lucide-file\",\"title\":\"202507302207 RAC - contents\"}",
                  "eState": "{\"cursor\":{\"from\":{\"line\":0,\"ch\":0},\"to\":{\"line\":0,\"ch\":0}}}"
                },
                {
                  "title": "202505222102 todolist solopreneur",
                  "icon": "lucide-file",
                  "state": "{\"type\":\"markdown\",\"state\":{\"file\":\"+/202505222102 todolist solopreneur.md\",\"mode\":\"source\",\"source\":false,\"backlinks\":true,\"backlinkOpts\":{\"collapseAll\":false,\"extraContext\":false,\"sortOrder\":\"alphabetical\",\"showSearch\":false,\"searchQuery\":\"\",\"backlinkCollapsed\":false,\"unlinkedCollapsed\":true}},\"icon\":\"lucide-file\",\"title\":\"202505222102 todolist solopreneur\"}",
                  "eState": "{\"cursor\":{\"from\":{\"line\":4,\"ch\":0},\"to\":{\"line\":4,\"ch\":0}},\"scroll\":0}"
                },
                {
                  "title": "202507302210 Justin welsh retro",
                  "icon": "lucide-file",
                  "state": "{\"type\":\"markdown\",\"state\":{\"file\":\"Clippings/202507302210 Justin welsh retro.md\",\"mode\":\"source\",\"source\":false,\"backlinks\":true,\"backlinkOpts\":{\"collapseAll\":false,\"extraContext\":false,\"sortOrder\":\"alphabetical\",\"showSearch\":false,\"searchQuery\":\"\",\"backlinkCollapsed\":false,\"unlinkedCollapsed\":true}},\"icon\":\"lucide-file\",\"title\":\"202507302210 Justin welsh retro\"}",
                  "eState": "{\"cursor\":{\"from\":{\"line\":162,\"ch\":0},\"to\":{\"line\":162,\"ch\":0}},\"scroll\":139.82486979166666}"
                }
              ]
            },
            "state": {
              "type": "markdown",
              "state": {
                "file": "Atlas/Projects/Zoimmeisdess/produits/RAC - Revenir en accord avec son corps/MOA RAC - Revenir en accord avec son corps.md",
                "mode": "source",
                "source": false,
                "backlinks": true,
                "backlinkOpts": {
                  "collapseAll": false,
                  "extraContext": false,
                  "sortOrder": "alphabetical",
                  "showSearch": false,
                  "searchQuery": "",
                  "backlinkCollapsed": false,
                  "unlinkedCollapsed": true
                }
              },
              "icon": "lucide-file",
              "title": "MOA RAC - Revenir en accord avec son corps"
            }
          },
          {
            "id": "c4244528f45d518f",
            "type": "leaf",
            "pane-relief:history-v1": {
              "pos": 0,
              "stack": [
                {
                  "state": "{}",
                  "eState": "{}"
                },
                {
                  "title": "20250801226 pensee plate - V1",
                  "icon": "lucide-file",
                  "state": "{\"type\":\"markdown\",\"state\":{\"file\":\"Atlas/Projects/Zoimmeisdess/contents/versions/20250801226 pensee plate - V1.md\",\"mode\":\"source\",\"source\":false,\"backlinks\":true,\"backlinkOpts\":{\"collapseAll\":false,\"extraContext\":false,\"sortOrder\":\"alphabetical\",\"showSearch\":false,\"searchQuery\":\"\",\"backlinkCollapsed\":false,\"unlinkedCollapsed\":true}},\"icon\":\"lucide-file\",\"title\":\"20250801226 pensee plate - V1\"}",
                  "eState": "{\"cursor\":{\"from\":{\"line\":0,\"ch\":0},\"to\":{\"line\":0,\"ch\":0}},\"scroll\":9.787760416666666}"
                },
                {
                  "title": "202508011755 contenu - pensee plate",
                  "icon": "lucide-file",
                  "state": "{\"type\":\"markdown\",\"state\":{\"file\":\"Atlas/Projects/Zoimmeisdess/contents/202508011755 contenu - pensee plate.md\",\"mode\":\"source\",\"source\":false,\"backlinks\":true,\"backlinkOpts\":{\"collapseAll\":false,\"extraContext\":false,\"sortOrder\":\"alphabetical\",\"showSearch\":false,\"searchQuery\":\"\",\"backlinkCollapsed\":false,\"unlinkedCollapsed\":true}},\"icon\":\"lucide-file\",\"title\":\"202508011755 contenu - pensee plate\"}",
                  "eState": "{\"cursor\":{\"from\":{\"line\":2,\"ch\":19},\"to\":{\"line\":2,\"ch\":19}},\"scroll\":0}"
                },
                {
                  "title": "202508012230 koe metrics",
                  "icon": "lucide-file",
                  "state": "{\"type\":\"markdown\",\"state\":{\"file\":\"Atlas/Projects/Zoimmeisdess/contents/versions/202508012230 koe metrics.md\",\"mode\":\"source\",\"source\":false,\"backlinks\":true,\"backlinkOpts\":{\"collapseAll\":false,\"extraContext\":false,\"sortOrder\":\"alphabetical\",\"showSearch\":false,\"searchQuery\":\"\",\"backlinkCollapsed\":false,\"unlinkedCollapsed\":true}},\"icon\":\"lucide-file\",\"title\":\"202508012230 koe metrics\"}",
                  "eState": "{\"cursor\":{\"from\":{\"line\":25,\"ch\":231},\"to\":{\"line\":25,\"ch\":231}},\"scroll\":17.102864583333332}"
                },
                {
                  "title": "202508011755 contenu - pensee plate",
                  "icon": "lucide-file",
                  "state": "{\"type\":\"markdown\",\"state\":{\"file\":\"Atlas/Projects/Zoimmeisdess/contents/202508011755 contenu - pensee plate.md\",\"mode\":\"source\",\"source\":false,\"backlinks\":true,\"backlinkOpts\":{\"collapseAll\":false,\"extraContext\":false,\"sortOrder\":\"alphabetical\",\"showSearch\":false,\"searchQuery\":\"\",\"backlinkCollapsed\":false,\"unlinkedCollapsed\":true}},\"icon\":\"lucide-file\",\"title\":\"202508011755 contenu - pensee plate\"}",
                  "eState": "{\"cursor\":{\"from\":{\"line\":5,\"ch\":24},\"to\":{\"line\":5,\"ch\":24}}}"
                },
                {
                  "title": "KOe metrics",
                  "icon": "lucide-file",
                  "state": "{\"type\":\"markdown\",\"state\":{\"file\":\"Atlas/Projects/Zoimmeisdess/prompting/luc/KOe metrics.md\",\"mode\":\"source\",\"source\":false,\"backlinks\":true,\"backlinkOpts\":{\"collapseAll\":false,\"extraContext\":false,\"sortOrder\":\"alphabetical\",\"showSearch\":false,\"searchQuery\":\"\",\"backlinkCollapsed\":false,\"unlinkedCollapsed\":true}},\"icon\":\"lucide-file\",\"title\":\"KOe metrics\"}",
                  "eState": "{\"cursor\":{\"from\":{\"line\":18,\"ch\":76},\"to\":{\"line\":18,\"ch\":76}}}"
                },
                {
                  "title": "202508011755 contenu - pensee plate",
                  "icon": "lucide-file",
                  "state": "{\"type\":\"markdown\",\"state\":{\"file\":\"Atlas/Projects/Zoimmeisdess/contents/202508011755 contenu - pensee plate.md\",\"mode\":\"source\",\"source\":false,\"backlinks\":true,\"backlinkOpts\":{\"collapseAll\":false,\"extraContext\":false,\"sortOrder\":\"alphabetical\",\"showSearch\":false,\"searchQuery\":\"\",\"backlinkCollapsed\":false,\"unlinkedCollapsed\":true}},\"icon\":\"lucide-file\",\"title\":\"202508011755 contenu - pensee plate\"}",
                  "eState": "{\"cursor\":{\"from\":{\"line\":5,\"ch\":0},\"to\":{\"line\":5,\"ch\":0}},\"scroll\":0}"
                },
                {
                  "title": "20250801229 analysis",
                  "icon": "lucide-file",
                  "state": "{\"type\":\"markdown\",\"state\":{\"file\":\"Atlas/Projects/Zoimmeisdess/contents/versions/20250801229 analysis.md\",\"mode\":\"source\",\"source\":false,\"backlinks\":true,\"backlinkOpts\":{\"collapseAll\":false,\"extraContext\":false,\"sortOrder\":\"alphabetical\",\"showSearch\":false,\"searchQuery\":\"\",\"backlinkCollapsed\":false,\"unlinkedCollapsed\":true}},\"icon\":\"lucide-file\",\"title\":\"20250801229 analysis\"}",
                  "eState": "{\"cursor\":{\"from\":{\"line\":114,\"ch\":103},\"to\":{\"line\":114,\"ch\":103}},\"scroll\":103.28660049627791}"
                },
                {
                  "title": "202508011755 contenu - pensee plate",
                  "icon": "lucide-file",
                  "state": "{\"type\":\"markdown\",\"state\":{\"file\":\"Atlas/Projects/Zoimmeisdess/contents/202508011755 contenu - pensee plate.md\",\"mode\":\"source\",\"source\":false,\"backlinks\":true,\"backlinkOpts\":{\"collapseAll\":false,\"extraContext\":false,\"sortOrder\":\"alphabetical\",\"showSearch\":false,\"searchQuery\":\"\",\"backlinkCollapsed\":false,\"unlinkedCollapsed\":true}},\"icon\":\"lucide-file\",\"title\":\"202508011755 contenu - pensee plate\"}",
                  "eState": "{\"cursor\":{\"from\":{\"line\":4,\"ch\":11},\"to\":{\"line\":4,\"ch\":11}},\"scroll\":0}"
                },
                {
                  "title": "20250801226 pensee plate - V1",
                  "icon": "lucide-file",
                  "state": "{\"type\":\"markdown\",\"state\":{\"file\":\"Atlas/Projects/Zoimmeisdess/contents/versions/20250801226 pensee plate - V1.md\",\"mode\":\"source\",\"source\":false,\"backlinks\":true,\"backlinkOpts\":{\"collapseAll\":false,\"extraContext\":false,\"sortOrder\":\"alphabetical\",\"showSearch\":false,\"searchQuery\":\"\",\"backlinkCollapsed\":false,\"unlinkedCollapsed\":true}},\"icon\":\"lucide-file\",\"title\":\"20250801226 pensee plate - V1\"}",
                  "eState": "{\"cursor\":{\"from\":{\"line\":0,\"ch\":0},\"to\":{\"line\":0,\"ch\":0}},\"scroll\":12.72265625}"
                },
                {
                  "title": "202508011755 contenu - pensee plate",
                  "icon": "lucide-file",
                  "state": "{\"type\":\"markdown\",\"state\":{\"file\":\"Atlas/Projects/Zoimmeisdess/contents/202508011755 contenu - pensee plate.md\",\"mode\":\"source\",\"source\":false,\"backlinks\":true,\"backlinkOpts\":{\"collapseAll\":false,\"extraContext\":false,\"sortOrder\":\"alphabetical\",\"showSearch\":false,\"searchQuery\":\"\",\"backlinkCollapsed\":false,\"unlinkedCollapsed\":true}},\"icon\":\"lucide-file\",\"title\":\"202508011755 contenu - pensee plate\"}",
                  "eState": "{\"cursor\":{\"from\":{\"line\":2,\"ch\":18},\"to\":{\"line\":2,\"ch\":18}},\"scroll\":0}"
                },
                {
                  "title": "202508011755 pensee plate - v0",
                  "icon": "lucide-file",
                  "state": "{\"type\":\"markdown\",\"state\":{\"file\":\"Atlas/Projects/Zoimmeisdess/contents/versions/202508011755 pensee plate - v0.md\",\"mode\":\"source\",\"source\":false,\"backlinks\":true,\"backlinkOpts\":{\"collapseAll\":false,\"extraContext\":false,\"sortOrder\":\"alphabetical\",\"showSearch\":false,\"searchQuery\":\"\",\"backlinkCollapsed\":false,\"unlinkedCollapsed\":true}},\"icon\":\"lucide-file\",\"title\":\"202508011755 pensee plate - v0\"}",
                  "eState": "{\"cursor\":{\"from\":{\"line\":2,\"ch\":28},\"to\":{\"line\":2,\"ch\":28}},\"scroll\":103.20638020833333}"
                },
                {
                  "title": "202508011755 contenu - pensee plate",
                  "icon": "lucide-file",
                  "state": "{\"type\":\"markdown\",\"state\":{\"file\":\"Atlas/Projects/Zoimmeisdess/contents/202508011755 contenu - pensee plate.md\",\"mode\":\"source\",\"source\":false,\"backlinks\":true,\"backlinkOpts\":{\"collapseAll\":false,\"extraContext\":false,\"sortOrder\":\"alphabetical\",\"showSearch\":false,\"searchQuery\":\"\",\"backlinkCollapsed\":false,\"unlinkedCollapsed\":true}},\"icon\":\"lucide-file\",\"title\":\"202508011755 contenu - pensee plate\"}",
                  "eState": "{\"cursor\":{\"from\":{\"line\":1,\"ch\":26},\"to\":{\"line\":1,\"ch\":26}},\"scroll\":0}"
                },
                {
                  "title": "floating context",
                  "icon": "lucide-file",
                  "state": "{\"type\":\"markdown\",\"state\":{\"file\":\"Atlas/Projects/Zoimmeisdess/prompting/luc/floating context.md\",\"mode\":\"source\",\"source\":false,\"backlinks\":true,\"backlinkOpts\":{\"collapseAll\":false,\"extraContext\":false,\"sortOrder\":\"alphabetical\",\"showSearch\":false,\"searchQuery\":\"\",\"backlinkCollapsed\":false,\"unlinkedCollapsed\":true}},\"icon\":\"lucide-file\",\"title\":\"floating context\"}",
                  "eState": "{\"cursor\":{\"from\":{\"line\":113,\"ch\":2},\"to\":{\"line\":136,\"ch\":268}},\"scroll\":149.3781017369727}"
                },
                {
                  "title": "202508011755 pensee plate - v0",
                  "icon": "lucide-file",
                  "state": "{\"type\":\"markdown\",\"state\":{\"file\":\"Atlas/Projects/Zoimmeisdess/contents/versions/202508011755 pensee plate - v0.md\",\"mode\":\"source\",\"source\":false,\"backlinks\":true,\"backlinkOpts\":{\"collapseAll\":false,\"extraContext\":false,\"sortOrder\":\"alphabetical\",\"showSearch\":false,\"searchQuery\":\"\",\"backlinkCollapsed\":false,\"unlinkedCollapsed\":true}},\"icon\":\"lucide-file\",\"title\":\"202501081755 pensee plate - v0\"}",
                  "eState": "{\"cursor\":{\"from\":{\"line\":0,\"ch\":0},\"to\":{\"line\":0,\"ch\":0}}}"
                },
                {
                  "title": "202508011755 contenu - pensee plate",
                  "icon": "lucide-file",
                  "state": "{\"type\":\"markdown\",\"state\":{\"file\":\"Atlas/Projects/Zoimmeisdess/contents/202508011755 contenu - pensee plate.md\",\"mode\":\"source\",\"source\":false,\"backlinks\":true,\"backlinkOpts\":{\"collapseAll\":false,\"extraContext\":false,\"sortOrder\":\"alphabetical\",\"showSearch\":false,\"searchQuery\":\"\",\"backlinkCollapsed\":false,\"unlinkedCollapsed\":true}},\"icon\":\"lucide-file\",\"title\":\"202508011755 contenu - pensee plate\"}",
                  "eState": "{\"cursor\":{\"from\":{\"line\":1,\"ch\":31},\"to\":{\"line\":1,\"ch\":31}},\"scroll\":0}"
                },
                {
                  "title": "20250801226 pensee plate - V1",
                  "icon": "lucide-file",
                  "state": "{\"type\":\"markdown\",\"state\":{\"file\":\"Atlas/Projects/Zoimmeisdess/contents/versions/20250801226 pensee plate - V1.md\",\"mode\":\"source\",\"source\":false,\"backlinks\":true,\"backlinkOpts\":{\"collapseAll\":false,\"extraContext\":false,\"sortOrder\":\"alphabetical\",\"showSearch\":false,\"searchQuery\":\"\",\"backlinkCollapsed\":false,\"unlinkedCollapsed\":true}},\"icon\":\"lucide-file\",\"title\":\"20250108226 pensee plate - V1\"}",
                  "eState": "{\"cursor\":{\"from\":{\"line\":17,\"ch\":419},\"to\":{\"line\":17,\"ch\":419}},\"scroll\":9.192522321428571}"
                },
                {
                  "title": "202508011755 contenu - pensee plate",
                  "icon": "lucide-file",
                  "state": "{\"type\":\"markdown\",\"state\":{\"file\":\"Atlas/Projects/Zoimmeisdess/contents/202508011755 contenu - pensee plate.md\",\"mode\":\"source\",\"source\":false,\"backlinks\":true,\"backlinkOpts\":{\"collapseAll\":false,\"extraContext\":false,\"sortOrder\":\"alphabetical\",\"showSearch\":false,\"searchQuery\":\"\",\"backlinkCollapsed\":false,\"unlinkedCollapsed\":true}},\"icon\":\"lucide-file\",\"title\":\"202508011755 contenu - pensee plate\"}",
                  "eState": "{\"cursor\":{\"from\":{\"line\":2,\"ch\":19},\"to\":{\"line\":2,\"ch\":19}},\"scroll\":0}"
                },
                {
                  "title": "202508011755 pensee plate - v0",
                  "icon": "lucide-file",
                  "state": "{\"type\":\"markdown\",\"state\":{\"file\":\"Atlas/Projects/Zoimmeisdess/contents/versions/202508011755 pensee plate - v0.md\",\"mode\":\"source\",\"source\":false,\"backlinks\":true,\"backlinkOpts\":{\"collapseAll\":false,\"extraContext\":false,\"sortOrder\":\"alphabetical\",\"showSearch\":false,\"searchQuery\":\"\",\"backlinkCollapsed\":false,\"unlinkedCollapsed\":true}},\"icon\":\"lucide-file\",\"title\":\"202501081755 pensee plate - v0\"}",
                  "eState": "{\"cursor\":{\"from\":{\"line\":0,\"ch\":0},\"to\":{\"line\":0,\"ch\":0}},\"scroll\":103.20638020833333}"
                },
                {
                  "title": "floating context",
                  "icon": "lucide-file",
                  "state": "{\"type\":\"markdown\",\"state\":{\"file\":\"Atlas/Projects/Zoimmeisdess/prompting/luc/floating context.md\",\"mode\":\"source\",\"source\":false,\"backlinks\":true,\"backlinkOpts\":{\"collapseAll\":false,\"extraContext\":false,\"sortOrder\":\"alphabetical\",\"showSearch\":false,\"searchQuery\":\"\",\"backlinkCollapsed\":false,\"unlinkedCollapsed\":true}},\"icon\":\"lucide-file\",\"title\":\"floating context\"}",
                  "eState": "{\"cursor\":{\"from\":{\"line\":243,\"ch\":137},\"to\":{\"line\":243,\"ch\":137}},\"scroll\":95.07001607717042}"
                },
                {
                  "title": "JARA logos",
                  "icon": "lucide-file",
                  "state": "{\"type\":\"markdown\",\"state\":{\"file\":\"Atlas/Projects/Zoimmeisdess/prompting/luc/JARA logos.md\",\"mode\":\"source\",\"source\":false,\"backlinks\":true,\"backlinkOpts\":{\"collapseAll\":false,\"extraContext\":false,\"sortOrder\":\"alphabetical\",\"showSearch\":false,\"searchQuery\":\"\",\"backlinkCollapsed\":false,\"unlinkedCollapsed\":true}},\"icon\":\"lucide-file\",\"title\":\"JARA logos\"}",
                  "eState": "{\"cursor\":{\"from\":{\"line\":73,\"ch\":429},\"to\":{\"line\":73,\"ch\":429}}}"
                },
                {
                  "title": "KOe metrics",
                  "icon": "lucide-file",
                  "state": "{\"type\":\"markdown\",\"state\":{\"file\":\"Atlas/Projects/Zoimmeisdess/prompting/luc/KOe metrics.md\",\"mode\":\"source\",\"source\":false,\"backlinks\":true,\"backlinkOpts\":{\"collapseAll\":false,\"extraContext\":false,\"sortOrder\":\"alphabetical\",\"showSearch\":false,\"searchQuery\":\"\",\"backlinkCollapsed\":false,\"unlinkedCollapsed\":true}},\"icon\":\"lucide-file\",\"title\":\"KOe metrics\"}",
                  "eState": "{\"cursor\":{\"from\":{\"line\":18,\"ch\":76},\"to\":{\"line\":18,\"ch\":76}}}"
                },
                {
                  "title": "202508011755 pensee plate - v0",
                  "icon": "lucide-file",
                  "state": "{\"type\":\"markdown\",\"state\":{\"file\":\"Atlas/Projects/Zoimmeisdess/contents/versions/202508011755 pensee plate - v0.md\",\"mode\":\"source\",\"source\":false,\"backlinks\":true,\"backlinkOpts\":{\"collapseAll\":false,\"extraContext\":false,\"sortOrder\":\"alphabetical\",\"showSearch\":false,\"searchQuery\":\"\",\"backlinkCollapsed\":false,\"unlinkedCollapsed\":true}},\"icon\":\"lucide-file\",\"title\":\"202501081755 pensee plate - v0\"}",
                  "eState": "{\"cursor\":{\"from\":{\"line\":113,\"ch\":203},\"to\":{\"line\":113,\"ch\":203}},\"scroll\":0}"
                },
                {
                  "title": "202508011755 contenu - pensee plate",
                  "icon": "lucide-file",
                  "state": "{\"type\":\"markdown\",\"state\":{\"file\":\"Atlas/Projects/Zoimmeisdess/contents/202508011755 contenu - pensee plate.md\",\"mode\":\"source\",\"source\":false,\"backlinks\":true,\"backlinkOpts\":{\"collapseAll\":false,\"extraContext\":false,\"sortOrder\":\"alphabetical\",\"showSearch\":false,\"searchQuery\":\"\",\"backlinkCollapsed\":false,\"unlinkedCollapsed\":true}},\"icon\":\"lucide-file\",\"title\":\"202508011755 contenu - pensee plate\"}",
                  "eState": "{\"cursor\":{\"from\":{\"line\":1,\"ch\":13},\"to\":{\"line\":1,\"ch\":13}}}"
                },
                {
                  "title": "1 - Zoimmeisdess Project",
                  "icon": "lucide-file",
                  "state": "{\"type\":\"markdown\",\"state\":{\"file\":\"Atlas/Projects/Zoimmeisdess/1 - Zoimmeisdess Project.md\",\"mode\":\"source\",\"source\":false,\"backlinks\":true,\"backlinkOpts\":{\"collapseAll\":false,\"extraContext\":false,\"sortOrder\":\"alphabetical\",\"showSearch\":false,\"searchQuery\":\"\",\"backlinkCollapsed\":false,\"unlinkedCollapsed\":true}},\"icon\":\"lucide-file\",\"title\":\"1 - Zoimmeisdess Project\"}",
                  "eState": "{\"cursor\":{\"from\":{\"line\":29,\"ch\":32},\"to\":{\"line\":29,\"ch\":32}},\"scroll\":14.825331971399388}"
                },
                {
                  "title": "202508011548 exemples de contenus 2",
                  "icon": "lucide-file",
                  "state": "{\"type\":\"markdown\",\"state\":{\"file\":\"+/202508011548 exemples de contenus 2.md\",\"mode\":\"source\",\"source\":false,\"backlinks\":true,\"backlinkOpts\":{\"collapseAll\":false,\"extraContext\":false,\"sortOrder\":\"alphabetical\",\"showSearch\":false,\"searchQuery\":\"\",\"backlinkCollapsed\":false,\"unlinkedCollapsed\":true}},\"icon\":\"lucide-file\",\"title\":\"202508011548 exemples de contenus 2\"}",
                  "eState": "{\"cursor\":{\"from\":{\"line\":95,\"ch\":154},\"to\":{\"line\":95,\"ch\":154}},\"scroll\":85.64993646759848}"
                },
                {
                  "title": "1 - Zoimmeisdess Project",
                  "icon": "lucide-file",
                  "state": "{\"type\":\"markdown\",\"state\":{\"file\":\"Atlas/Projects/Zoimmeisdess/1 - Zoimmeisdess Project.md\",\"mode\":\"source\",\"source\":false,\"backlinks\":true,\"backlinkOpts\":{\"collapseAll\":false,\"extraContext\":false,\"sortOrder\":\"alphabetical\",\"showSearch\":false,\"searchQuery\":\"\",\"backlinkCollapsed\":false,\"unlinkedCollapsed\":true}},\"icon\":\"lucide-file\",\"title\":\"1 - Zoimmeisdess Project\"}",
                  "eState": "{\"cursor\":{\"from\":{\"line\":28,\"ch\":32},\"to\":{\"line\":28,\"ch\":32}},\"scroll\":14.825331971399388}"
                },
                {
                  "title": "202508011544 exemples de contenus",
                  "icon": "lucide-file",
                  "state": "{\"type\":\"markdown\",\"state\":{\"file\":\"+/202508011544 exemples de contenus.md\",\"mode\":\"source\",\"source\":false,\"backlinks\":true,\"backlinkOpts\":{\"collapseAll\":false,\"extraContext\":false,\"sortOrder\":\"alphabetical\",\"showSearch\":false,\"searchQuery\":\"\",\"backlinkCollapsed\":false,\"unlinkedCollapsed\":true}},\"icon\":\"lucide-file\",\"title\":\"202508011544 exemples de contenus\"}",
                  "eState": "{\"cursor\":{\"from\":{\"line\":96,\"ch\":146},\"to\":{\"line\":96,\"ch\":146}},\"scroll\":83.796875}"
                },
                {
                  "title": "1 - Zoimmeisdess Project",
                  "icon": "lucide-file",
                  "state": "{\"type\":\"markdown\",\"state\":{\"file\":\"Atlas/Projects/Zoimmeisdess/1 - Zoimmeisdess Project.md\",\"mode\":\"source\",\"source\":false,\"backlinks\":true,\"backlinkOpts\":{\"collapseAll\":false,\"extraContext\":false,\"sortOrder\":\"alphabetical\",\"showSearch\":false,\"searchQuery\":\"\",\"backlinkCollapsed\":false,\"unlinkedCollapsed\":true}},\"icon\":\"lucide-file\",\"title\":\"1 - Zoimmeisdess Project\"}",
                  "eState": "{\"cursor\":{\"from\":{\"line\":27,\"ch\":28},\"to\":{\"line\":27,\"ch\":28}},\"scroll\":14.008171603677221}"
                },
                {
                  "title": "202508011425 polydeme",
                  "icon": "lucide-file",
                  "state": "{\"type\":\"markdown\",\"state\":{\"file\":\"+/202508011425 polydeme.md\",\"mode\":\"source\",\"source\":false,\"backlinks\":true,\"backlinkOpts\":{\"collapseAll\":false,\"extraContext\":false,\"sortOrder\":\"alphabetical\",\"showSearch\":false,\"searchQuery\":\"\",\"backlinkCollapsed\":false,\"unlinkedCollapsed\":true}},\"icon\":\"lucide-file\",\"title\":\"202508011425 polydeme\"}",
                  "eState": "{\"cursor\":{\"from\":{\"line\":375,\"ch\":130},\"to\":{\"line\":375,\"ch\":130}},\"scroll\":248.91788401947764}"
                }
              ]
            },
            "state": {
              "type": "markdown",
              "state": {
                "file": "Atlas/Projects/Zoimmeisdess/prompting/luc/floating context.md",
                "mode": "source",
                "source": false,
                "backlinks": true,
                "backlinkOpts": {
                  "collapseAll": false,
                  "extraContext": false,
                  "sortOrder": "alphabetical",
                  "showSearch": false,
                  "searchQuery": "",
                  "backlinkCollapsed": false,
                  "unlinkedCollapsed": true
                }
              },
              "icon": "lucide-file",
              "title": "floating context"
            }
          }
        ],
        "currentTab": 1
      }
    ],
    "direction": "vertical"
  },
  "left": {
    "id": "440b3841429709ed",
    "type": "split",
    "children": [
      {
        "id": "b208c03cadd231ee",
        "type": "tabs",
        "children": [
          {
            "id": "dddbab8b18fd423a",
            "type": "leaf",
            "pane-relief:history-v1": {
              "pos": 0,
              "stack": [
                {
                  "state": "{}",
                  "eState": "{}"
                }
              ]
            },
            "state": {
              "type": "file-explorer",
              "state": {
                "sortOrder": "alphabetical",
                "autoReveal": false
              },
              "icon": "lucide-folder-closed",
              "title": "Files"
            }
          },
          {
            "id": "1dc0cb1cebc39098",
            "type": "leaf",
            "pane-relief:history-v1": {
              "pos": 0,
              "stack": [
                {
                  "state": "{}",
                  "eState": "{}"
                }
              ]
            },
            "state": {
              "type": "calendar",
              "state": {},
              "icon": "calendar-with-checkmark",
              "title": "Calendar"
            }
          }
        ]
      }
    ],
    "direction": "horizontal",
    "width": 506
  },
  "right": {
    "id": "7a43a6c530e72e44",
    "type": "split",
    "children": [
      {
        "id": "ea89fdbc5439f479",
        "type": "tabs",
        "dimension": 62.64916467780429,
        "children": [
          {
            "id": "90d026528dc7103b",
            "type": "leaf",
            "pane-relief:history-v1": {
              "pos": 0,
              "stack": [
                {
                  "state": "{}",
                  "eState": "{}"
                }
              ]
            },
            "state": {
              "type": "outline",
              "state": {
                "file": "Efforts/Explorations/4E Cognition.md"
              },
              "icon": "lucide-list",
              "title": "Outline of 4E Cognition"
            }
          },
          {
            "id": "77966b04a7f238ed",
            "type": "leaf",
            "pane-relief:history-v1": {
              "pos": 0,
              "stack": [
                {
                  "state": "{}",
                  "eState": "{}"
                }
              ]
            },
            "state": {
              "type": "search",
              "state": {
                "query": "tag:kenWilber",
                "matchingCase": false,
                "explainSearch": false,
                "collapseAll": true,
                "extraContext": false,
                "sortOrder": "byModifiedTime"
              },
              "icon": "lucide-search",
              "title": "Search"
            }
          },
          {
            "id": "4f6e4ddebde66a86",
            "type": "leaf",
            "pane-relief:history-v1": {
              "pos": 0,
              "stack": [
                {
                  "state": "{}",
                  "eState": "{}"
                }
              ]
            },
            "state": {
              "type": "tag",
              "state": {
                "sortOrder": "alphabetical",
                "useHierarchy": true
              },
              "icon": "lucide-tags",
              "title": "Tags"
            }
          },
          {
            "id": "6f40109e4f78eb6c",
            "type": "leaf",
            "pane-relief:history-v1": {
              "pos": 0,
              "stack": [
                {
                  "state": "{}",
                  "eState": "{}"
                }
              ]
            },
            "state": {
              "type": "all-properties",
              "state": {
                "sortOrder": "frequency",
                "showSearch": false,
                "searchQuery": ""
              },
              "icon": "lucide-archive",
              "title": "All properties"
            }
          }
        ],
        "currentTab": 1
      },
      {
        "id": "8e15cd93a6a4be64",
        "type": "tabs",
        "dimension": 37.3508353221957,
        "children": [
          {
            "id": "d535bd36dbc98e0b",
            "type": "leaf",
            "pane-relief:history-v1": {
              "pos": 0,
              "stack": [
                {
                  "state": "{}",
                  "eState": "{}"
                }
              ]
            },
            "state": {
              "type": "backlink",
              "state": {
                "file": "Atlas/Projects/Zoimmeisdess/prompting/contexte zoimmeisdess/202505182215 contexte du jour.md",
                "collapseAll": true,
                "extraContext": false,
                "sortOrder": "alphabetical",
                "showSearch": false,
                "searchQuery": "",
                "backlinkCollapsed": false,
                "unlinkedCollapsed": true
              },
              "icon": "links-coming-in",
              "title": "Backlinks for 202505182215 contexte du jour"
            }
          },
          {
            "id": "ae0aed29d208c352",
            "type": "leaf",
            "pane-relief:history-v1": {
              "pos": 0,
              "stack": [
                {
                  "state": "{}",
                  "eState": "{}"
                }
              ]
            },
            "state": {
              "type": "outgoing-link",
              "state": {
                "file": "Efforts/Evideos/Vidéo - conf outils.md",
                "linksCollapsed": false,
                "unlinkedCollapsed": true
              },
              "icon": "links-going-out",
              "title": "Outgoing links from Vidéo - conf outils"
            }
          }
        ]
      }
    ],
    "direction": "horizontal",
    "width": 252.5,
    "collapsed": true
  },
  "left-ribbon": {
    "hiddenItems": {
      "quickadd:QuickAdd": false,
      "daily-notes:Open today's daily note": false,
      "publish:Publish changes...": false,
      "command-palette:Open command palette": false,
      "templates:Insert template": false,
      "switcher:Open quick switcher": false,
      "graph:Open graph view": false,
      "canvas:Create new canvas": false,
      "workspaces:Manage workspace layouts": false,
      "periodic-notes:Open today's daily note": false,
      "darlal-switcher-plus:Open in Headings Mode": false,
      "darlal-switcher-plus:Open Symbols for the active editor": false,
      "obsidian42-brat:BRAT": false,
      "cmdr:Toggle stacked tabs": false,
      "callout-manager:Insert Callout": false,
      "obsidian-excalidraw-plugin:New drawing": false,
      "audio-recorder:Start/stop recording": false
    }
  },
  "active": "c4244528f45d518f",
  "lastOpenFiles": [
    "Atlas/Projects/Zoimmeisdess/contents/versions/20250801226 pensee plate - V1.md",
    "Atlas/Projects/Zoimmeisdess/contents/202508011755 contenu - pensee plate.md",
    "Atlas/Projects/Zoimmeisdess/contents/versions/202508012230 koe metrics.md",
    "Atlas/Projects/Zoimmeisdess/prompting/luc/KOe metrics.md",
    "Atlas/Projects/Zoimmeisdess/contents/versions/20250801229 analysis.md",
    "Atlas/Projects/Zoimmeisdess/contents/versions/202508011755 pensee plate - v0.md",
    "Atlas/Projects/Zoimmeisdess/prompting/luc/floating context.md",
    "Atlas/Projects/Zoimmeisdess/prompting/luc/JARA logos.md",
    "Atlas/Projects/Zoimmeisdess/1 - Zoimmeisdess Project.md",
    "+/202508011548 exemples de contenus 2.md",
    "+/202508011544 exemples de contenus.md",
    "+/202508011425 polydeme.md",
    "Atlas/Projects/Zoimmeisdess/produits/RAC - Revenir en accord avec son corps/MOA RAC - Revenir en accord avec son corps.md",
    "Atlas/Projects/Zoimmeisdess/produits/RAC - Revenir en accord avec son corps/202507302207 RAC - contents.md",
    "Atlas/Notes/Ideas/202507310837 peur de l'echec enneagramme.md",
    "Atlas/Maps/Enneagramme.md",
    "+/202507311051 RAC - concurrence.md",
    "+/202507311038 RAC - V3.md",
    "Atlas/Projects/Zoimmeisdess/produits/RAC - Revenir en accord avec son corps/202507302245 RAC - V2.md",
    "Atlas/Projects/Zoimmeisdess/produits/RAC - Revenir en accord avec son corps/202507302208 RAC - Coach solopreneur.md",
    "Atlas/Projects/Zoimmeisdess/prompting/dragon 2/results/202507072207 société secrete, construction d un reseau d influence.md",
    "Atlas/Projects/Zoimmeisdess/prompting/dragon 2/202506292235 dragon 2.md",
    "Atlas/Notes/BooksNotes/202507112258 NL 24.md",
    "Atlas/Notes/BooksNotes/202507112258 NL 23.md",
    "Atlas/Notes/BooksNotes/202507112258 NL 8.md",
    "Atlas/Maps/Integral.md",
    "Atlas/Utilities/Images/integral24_1.png",
    "Atlas/Utilities/Images/integral23_1.png",
    "Atlas/Utilities/Images/enenatype_convergence_1-6.png",
    "Atlas/Utilities/Images/enenatype_convergence_2-9.png",
    "Atlas/Utilities/Images/enenatype_convergence_4-5.png",
    "Atlas/Utilities/Images/enenatype_convergence_3-7.png",
    "Atlas/Utilities/Images/enenatype_convergence_3-8.png",
    "Atlas/Utilities/Images/integral22_1.png",
    "Atlas/Utilities/Images/integral22_2.jpg",
    "Atlas/Utilities/Images/integral21_1.png",
    "Atlas/Projects/Zoimmeisdess/produits/RAC - Revenir en accord avec son corps",
    "Atlas/Projects/Zoimmeisdess/prompting/dragon 2/results",
    "Atlas/Projects/Zoimmeisdess/prompting/dragon 2",
    "Atlas/Projects/Zoimmeisdess/prompting/yihaio/result",
    "Atlas/Projects/Zoimmeisdess/prompting/yihaio",
    "Atlas/Utilities/sources/Human-Design-Blueprint-8318e3a9adc399eb53309795b5eb8ed6.pdf",
    "Atlas/Projects/Zoimmeisdess/prompting/conf sd/result",
    "Atlas/Projects/Zoimmeisdess/prompting/conf sd",
    "Atlas/Projects/Zoimmeisdess/prompting/copywritingluc/runaway",
    "Atlas/Projects/Zoimmeisdess/prompting/copywritingluc",
    "Atlas/Utilities/Canvases/2023-03-20 - Review, Brain Dump, Imagine, Prioritize.canvas",
    "Atlas/Utilities/Canvases/LYT W10 Calendar Canvas.canvas",
    "Atlas/Utilities/Canvases/LYT Ship Dashboard.canvas",
    "Atlas/Utilities/Canvases/LYT W11 Calendar Canvas.canvas",
    "Atlas/Utilities/Canvases/Obsidian Canvas MOC.canvas",
    "Atlas/Utilities/Canvases/Ship of the Sensemaker.canvas",
    "Atlas/Utilities/Canvases/LYT 2023 Rules.canvas",
    "Atlas/Utilities/Canvases/LYT Book Framing.canvas",
    "Atlas/Utilities/Canvases/LYT Nick Weekly Schedule.canvas",
    "Atlas/Utilities/Canvases/LYT Website Ideaverse.canvas"
  ]
}